dataframe_quickview/__init__.py
dataframe_quickview-0.1.1.dist-info/LICENSE
dataframe_quickview-0.1.1.dist-info/METADATA
dataframe_quickview-0.1.1.dist-info/WHEEL
dataframe_quickview-0.1.1.dist-info/top_level.txt
dataframe_quickview-0.1.1.dist-info/RECORD
