Metadata-Version: 2.1
Name: dataframe-quickview
Version: 0.1.1
Summary: A simple package to extend pandas DataFrame functionality for web-based visualization
Home-page: https://github.com/gittb/dataframe-quickview
Author: Ben Gitter
Author-email: gittebd@gmail.com
Classifier: Development Status :: 3 - Alpha
Classifier: Intended Audience :: Developers
Classifier: License :: OSI Approved :: MIT License
Classifier: Programming Language :: Python :: 3
Classifier: Programming Language :: Python :: 3.6
Classifier: Programming Language :: Python :: 3.7
Classifier: Programming Language :: Python :: 3.8
Classifier: Programming Language :: Python :: 3.9
Requires-Python: >=3.6
License-File: LICENSE
Requires-Dist: Flask (>=2.0.1)
Requires-Dist: pandas (>=1.3.0)
Requires-Dist: Flask-Testing (>=0.8.0)
